auto_graphql/__init__.py
auto_graphql/apps.py
auto_graphql/urls.py
auto_graphql/views.py
django_auto_graphql-0.1.0.dist-info/METADATA
django_auto_graphql-0.1.0.dist-info/WHEEL
django_auto_graphql-0.1.0.dist-info/top_level.txt
django_auto_graphql-0.1.0.dist-info/RECORD
