Metadata-Version: 2.1
Name: django-auto-graphql
Version: 0.1.0
Summary: an automatic GraphQL API for all the models in a Django project
Home-page: https://github.com/olegkishenkov/django-auto-graphql
Author: olegkishenkov
Author-email: Oleg Kishenkov <oleg.kishenkov@gmail.com>
Project-URL: Homepage, https://github.com/olegkishenkov/django-auto-graphql
Classifier: Programming Language :: Python :: 3
Classifier: License :: OSI Approved :: MIT License
Classifier: Operating System :: OS Independent
Requires-Python: >=3.8.1
